tessproposaltool/__init__.py
tessproposaltool/tpt.py
tessproposaltool-0.1.4.dist-info/LICENSE
tessproposaltool-0.1.4.dist-info/METADATA
tessproposaltool-0.1.4.dist-info/WHEEL
tessproposaltool-0.1.4.dist-info/entry_points.txt
tessproposaltool-0.1.4.dist-info/RECORD
