Metadata-Version: 2.3
Name: tessproposaltool
Version: 0.1.4
Summary: 
Author: Christina Hedges
Author-email: christina.l.hedges@nasa.gov
Requires-Python: >=3.9,<4.0.0
Classifier: Programming Language :: Python :: 3
Classifier: Programming Language :: Python :: 3.9
Classifier: Programming Language :: Python :: 3.10
Classifier: Programming Language :: Python :: 3.11
Classifier: Programming Language :: Python :: 3.12
Classifier: Programming Language :: Python :: 3.13
Requires-Dist: astropy (>=6.0.1,<7.0.0)
Requires-Dist: astroquery (>0.4.7)
Requires-Dist: asyncio (>=3.4.3,<4.0.0)
Requires-Dist: lksearch (>=1.1.0)
Requires-Dist: lxml (>=5.2.1,<6.0.0)
Requires-Dist: numpy (>=1.26.4,<2.0.0)
Requires-Dist: pandas (>=2.2.2,<3.0.0)
Requires-Dist: rich (>=13.7.1,<14.0.0)
Requires-Dist: tqdm (>=4.66.2,<5.0.0)
